CHANGELOG.txt
LICENCE.txt
MANIFEST.in
README.txt
setup.py
raztools/__init__.py
raztools.egg-info/PKG-INFO
raztools.egg-info/SOURCES.txt
raztools.egg-info/dependency_links.txt
raztools.egg-info/top_level.txt