Metadata-Version: 1.1
Name: raztools
Version: 0.0.1
Summary: A basic tool that allows you to do lots of things.
Home-page: UNKNOWN
Author: Razvan Iacob
Author-email: razvaniacob2008@gmail.com
License: MIT
Keywords: calculator
Platform: UNKNOWN
Classifier: Development Status :: 5 - Production/Stable
Classifier: Intended Audience :: Education
Classifier: Operating System :: Microsoft :: Windows :: Windows 10
Classifier: License :: OSI Approved :: MIT License
Classifier: Programming Language :: Python :: 3
